{
  "state": "arizona",
  "folds": 5,
  "epochs": 50,
  "seed": 42,
  "input_type": "region",
  "n_regions": 1540,
  "heads": {
    "next_getnext_hard": {
      "per_fold": [
        {
          "accuracy": 0.2443181872367859,
          "accuracy_macro": 0.07393212429312772,
          "f1": 0.06530274450778961,
          "f1_weighted": 0.21358391642570496,
          "mrr": 0.3311261832714081,
          "top5_acc": 0.42424243688583374,
          "ndcg_5": 0.33880457282066345,
          "top10_acc": 0.49753788113594055,
          "ndcg_10": 0.36233431100845337,
          "best_epoch": 32,
          "per_metric_best": {
            "accuracy": {
              "accuracy": 0.25303030014038086,
              "accuracy_macro": 0.08245670991785387,
              "f1": 0.07129298150539398,
              "f1_weighted": 0.2194967418909073,
              "mrr": 0.3355027139186859,
              "top5_acc": 0.41969695687294006,
              "ndcg_5": 0.34059837460517883,
              "top10_acc": 0.49299243092536926,
              "ndcg_10": 0.36436039209365845,
              "best_epoch": 26
            },
            "top5_acc": {
              "accuracy": 0.2443181872367859,
              "accuracy_macro": 0.07393212429312772,
              "f1": 0.06530274450778961,
              "f1_weighted": 0.21358391642570496,
              "mrr": 0.3311261832714081,
              "top5_acc": 0.42424243688583374,
              "ndcg_5": 0.33880457282066345,
              "top10_acc": 0.49753788113594055,
              "ndcg_10": 0.36233431100845337,
              "best_epoch": 32
            },
            "top10_acc": {
              "accuracy": 0.2443181872367859,
              "accuracy_macro": 0.07393212429312772,
              "f1": 0.06530274450778961,
              "f1_weighted": 0.21358391642570496,
              "mrr": 0.3311261832714081,
              "top5_acc": 0.42424243688583374,
              "ndcg_5": 0.33880457282066345,
              "top10_acc": 0.49753788113594055,
              "ndcg_10": 0.36233431100845337,
              "best_epoch": 32
            },
            "mrr": {
              "accuracy": 0.25303030014038086,
              "accuracy_macro": 0.08245670991785387,
              "f1": 0.07129298150539398,
              "f1_weighted": 0.2194967418909073,
              "mrr": 0.3355027139186859,
              "top5_acc": 0.41969695687294006,
              "ndcg_5": 0.34059837460517883,
              "top10_acc": 0.49299243092536926,
              "ndcg_10": 0.36436039209365845,
              "best_epoch": 26
            },
            "f1": {
              "accuracy": 0.2496212124824524,
              "accuracy_macro": 0.08235171893695453,
              "f1": 0.07344359904527664,
              "f1_weighted": 0.22781534492969513,
              "mrr": 0.3325140178203583,
              "top5_acc": 0.41856059432029724,
              "ndcg_5": 0.3379797339439392,
              "top10_acc": 0.49242424964904785,
              "ndcg_10": 0.3619309067726135,
              "best_epoch": 41
            }
          }
        },
        {
          "accuracy": 0.2561091184616089,
          "accuracy_macro": 0.08306121826171875,
          "f1": 0.07223135232925415,
          "f1_weighted": 0.2236625999212265,
          "mrr": 0.3412189483642578,
          "top5_acc": 0.42792195081710815,
          "ndcg_5": 0.34689265489578247,
          "top10_acc": 0.504641056060791,
          "ndcg_10": 0.37171921133995056,
          "best_epoch": 37,
          "per_metric_best": {
            "accuracy": {
              "accuracy": 0.2657700181007385,
              "accuracy_macro": 0.08849396576752534,
              "f1": 0.07528245449066162,
              "f1_weighted": 0.22966201603412628,
              "mrr": 0.34881436824798584,
              "top5_acc": 0.4320894181728363,
              "ndcg_5": 0.353976309299469,
              "top10_acc": 0.5040727257728577,
              "ndcg_10": 0.37709274888038635,
              "best_epoch": 28
            },
            "top5_acc": {
              "accuracy": 0.26330745220184326,
              "accuracy_macro": 0.08628104981921968,
              "f1": 0.07134785503149033,
              "f1_weighted": 0.2218121886253357,
              "mrr": 0.3460327982902527,
              "top5_acc": 0.43284714221954346,
              "ndcg_5": 0.35224926471710205,
              "top10_acc": 0.5033150315284729,
              "ndcg_10": 0.37494155764579773,
              "best_epoch": 25
            },
            "top10_acc": {
              "accuracy": 0.2561091184616089,
              "accuracy_macro": 0.08306121826171875,
              "f1": 0.07223135232925415,
              "f1_weighted": 0.2236625999212265,
              "mrr": 0.3412189483642578,
              "top5_acc": 0.42792195081710815,
              "ndcg_5": 0.34689265489578247,
              "top10_acc": 0.504641056060791,
              "ndcg_10": 0.37171921133995056,
              "best_epoch": 37
            },
            "mrr": {
              "accuracy": 0.2657700181007385,
              "accuracy_macro": 0.08849396576752534,
              "f1": 0.07528245449066162,
              "f1_weighted": 0.22966201603412628,
              "mrr": 0.34881436824798584,
              "top5_acc": 0.4320894181728363,
              "ndcg_5": 0.353976309299469,
              "top10_acc": 0.5040727257728577,
              "ndcg_10": 0.37709274888038635,
              "best_epoch": 28
            },
            "f1": {
              "accuracy": 0.2557302415370941,
              "accuracy_macro": 0.08758720320186421,
              "f1": 0.07761994749307632,
              "f1_weighted": 0.22737546265125275,
              "mrr": 0.3407498896121979,
              "top5_acc": 0.4241333603858948,
              "ndcg_5": 0.3454868495464325,
              "top10_acc": 0.4983898401260376,
              "ndcg_10": 0.36954742670059204,
              "best_epoch": 48
            }
          }
        },
        {
          "accuracy": 0.26198142766952515,
          "accuracy_macro": 0.07668711182418143,
          "f1": 0.06316039711236954,
          "f1_weighted": 0.21214063465595245,
          "mrr": 0.3499537408351898,
          "top5_acc": 0.43966659903526306,
          "ndcg_5": 0.3560132682323456,
          "top10_acc": 0.5196059942245483,
          "ndcg_10": 0.3817709684371948,
          "best_epoch": 22,
          "per_metric_best": {
            "accuracy": {
              "accuracy": 0.2710740566253662,
              "accuracy_macro": 0.08609532265767564,
              "f1": 0.07328814268112183,
              "f1_weighted": 0.23537121713161469,
              "mrr": 0.356148898601532,
              "top5_acc": 0.4419397711753845,
              "ndcg_5": 0.3618951141834259,
              "top10_acc": 0.5116499066352844,
              "ndcg_10": 0.38441601395606995,
              "best_epoch": 30
            },
            "top5_acc": {
              "accuracy": 0.2710740566253662,
              "accuracy_macro": 0.08609532265767564,
              "f1": 0.07328814268112183,
              "f1_weighted": 0.23537121713161469,
              "mrr": 0.356148898601532,
              "top5_acc": 0.4419397711753845,
              "ndcg_5": 0.3618951141834259,
              "top10_acc": 0.5116499066352844,
              "ndcg_10": 0.38441601395606995,
              "best_epoch": 30
            },
            "top10_acc": {
              "accuracy": 0.26198142766952515,
              "accuracy_macro": 0.07668711182418143,
              "f1": 0.06316039711236954,
              "f1_weighted": 0.21214063465595245,
              "mrr": 0.3499537408351898,
              "top5_acc": 0.43966659903526306,
              "ndcg_5": 0.3560132682323456,
              "top10_acc": 0.5196059942245483,
              "ndcg_10": 0.3817709684371948,
              "best_epoch": 22
            },
            "mrr": {
              "accuracy": 0.2710740566253662,
              "accuracy_macro": 0.08609532265767564,
              "f1": 0.07328814268112183,
              "f1_weighted": 0.23537121713161469,
              "mrr": 0.356148898601532,
              "top5_acc": 0.4419397711753845,
              "ndcg_5": 0.3618951141834259,
              "top10_acc": 0.5116499066352844,
              "ndcg_10": 0.38441601395606995,
              "best_epoch": 30
            },
            "f1": {
              "accuracy": 0.2665277421474457,
              "accuracy_macro": 0.08702013055575696,
              "f1": 0.07788269966840744,
              "f1_weighted": 0.23905137181282043,
              "mrr": 0.3511960506439209,
              "top5_acc": 0.4370145797729492,
              "ndcg_5": 0.3566736578941345,
              "top10_acc": 0.5122182369232178,
              "ndcg_10": 0.38092878460884094,
              "best_epoch": 43
            }
          }
        },
        {
          "accuracy": 0.20609964430332184,
          "accuracy_macro": 0.06942914311973095,
          "f1": 0.05845700204372406,
          "f1_weighted": 0.16780567169189453,
          "mrr": 0.28831905126571655,
          "top5_acc": 0.3710930049419403,
          "ndcg_5": 0.2921503186225891,
          "top10_acc": 0.4489486515522003,
          "ndcg_10": 0.3173741400241852,
          "best_epoch": 23,
          "per_metric_best": {
            "accuracy": {
              "accuracy": 0.2168971449136734,
              "accuracy_macro": 0.08031154203801691,
              "f1": 0.06814541667699814,
              "f1_weighted": 0.18904411792755127,
              "mrr": 0.29397085309028625,
              "top5_acc": 0.3691987097263336,
              "ndcg_5": 0.2961283326148987,
              "top10_acc": 0.44648608565330505,
              "ndcg_10": 0.3211095631122589,
              "best_epoch": 29
            },
            "top5_acc": {
              "accuracy": 0.20609964430332184,
              "accuracy_macro": 0.07447619063633408,
              "f1": 0.062888003885746,
              "f1_weighted": 0.17137736082077026,
              "mrr": 0.28914597630500793,
              "top5_acc": 0.3746921718120575,
              "ndcg_5": 0.29425814747810364,
              "top10_acc": 0.4438340663909912,
              "ndcg_10": 0.3167060613632202,
              "best_epoch": 25
            },
            "top10_acc": {
              "accuracy": 0.20609964430332184,
              "accuracy_macro": 0.06942914311973095,
              "f1": 0.05845700204372406,
              "f1_weighted": 0.16780567169189453,
              "mrr": 0.28831905126571655,
              "top5_acc": 0.3710930049419403,
              "ndcg_5": 0.2921503186225891,
              "top10_acc": 0.4489486515522003,
              "ndcg_10": 0.3173741400241852,
              "best_epoch": 23
            },
            "mrr": {
              "accuracy": 0.2168971449136734,
              "accuracy_macro": 0.08031154203801691,
              "f1": 0.06814541667699814,
              "f1_weighted": 0.18904411792755127,
              "mrr": 0.29397085309028625,
              "top5_acc": 0.3691987097263336,
              "ndcg_5": 0.2961283326148987,
              "top10_acc": 0.44648608565330505,
              "ndcg_10": 0.3211095631122589,
              "best_epoch": 29
            },
            "f1": {
              "accuracy": 0.20647850632667542,
              "accuracy_macro": 0.079994839569398,
              "f1": 0.06958753615617752,
              "f1_weighted": 0.1848386526107788,
              "mrr": 0.28810280561447144,
              "top5_acc": 0.36881986260414124,
              "ndcg_5": 0.29211363196372986,
              "top10_acc": 0.44345518946647644,
              "ndcg_10": 0.3162391483783722,
              "best_epoch": 38
            }
          }
        },
        {
          "accuracy": 0.2644440233707428,
          "accuracy_macro": 0.07967006296351337,
          "f1": 0.07033563405275345,
          "f1_weighted": 0.22406896948814392,
          "mrr": 0.34894829988479614,
          "top5_acc": 0.4360674321651459,
          "ndcg_5": 0.35517245531082153,
          "top10_acc": 0.5097556114196777,
          "ndcg_10": 0.378965824842453,
          "best_epoch": 23,
          "per_metric_best": {
            "accuracy": {
              "accuracy": 0.26709604263305664,
              "accuracy_macro": 0.08975918940214436,
              "f1": 0.07991936057806015,
              "f1_weighted": 0.24093720316886902,
              "mrr": 0.35003796219825745,
              "top5_acc": 0.4307633936405182,
              "ndcg_5": 0.35423544049263,
              "top10_acc": 0.5080507397651672,
              "ndcg_10": 0.37930411100387573,
              "best_epoch": 33
            },
            "top5_acc": {
              "accuracy": 0.26198142766952515,
              "accuracy_macro": 0.0792797518448091,
              "f1": 0.07054746150970459,
              "f1_weighted": 0.22803710401058197,
              "mrr": 0.34589967131614685,
              "top5_acc": 0.43625685572624207,
              "ndcg_5": 0.35312387347221375,
              "top10_acc": 0.5061564445495605,
              "ndcg_10": 0.3758130371570587,
              "best_epoch": 30
            },
            "top10_acc": {
              "accuracy": 0.2644440233707428,
              "accuracy_macro": 0.07967006296351337,
              "f1": 0.07033563405275345,
              "f1_weighted": 0.22406896948814392,
              "mrr": 0.34894829988479614,
              "top5_acc": 0.4360674321651459,
              "ndcg_5": 0.35517245531082153,
              "top10_acc": 0.5097556114196777,
              "ndcg_10": 0.378965824842453,
              "best_epoch": 23
            },
            "mrr": {
              "accuracy": 0.26709604263305664,
              "accuracy_macro": 0.08975918940214436,
              "f1": 0.07991936057806015,
              "f1_weighted": 0.24093720316886902,
              "mrr": 0.35003796219825745,
              "top5_acc": 0.4307633936405182,
              "ndcg_5": 0.35423544049263,
              "top10_acc": 0.5080507397651672,
              "ndcg_10": 0.37930411100387573,
              "best_epoch": 33
            },
            "f1": {
              "accuracy": 0.26709604263305664,
              "accuracy_macro": 0.08975918940214436,
              "f1": 0.07991936057806015,
              "f1_weighted": 0.24093720316886902,
              "mrr": 0.35003796219825745,
              "top5_acc": 0.4307633936405182,
              "ndcg_5": 0.35423544049263,
              "top10_acc": 0.5080507397651672,
              "ndcg_10": 0.37930411100387573,
              "best_epoch": 33
            }
          }
        }
      ],
      "aggregate": {
        "accuracy_mean": 0.2465904802083969,
        "accuracy_std": 0.02393170412359417,
        "top5_acc_mean": 0.4197982847690582,
        "top5_acc_std": 0.02791676821334914,
        "top10_acc_mean": 0.49609783887863157,
        "top10_acc_std": 0.0275557356353355,
        "mrr_mean": 0.3319132447242737,
        "mrr_std": 0.02551137929198424,
        "f1_mean": 0.06589742600917817,
        "f1_std": 0.005545746012079228
      },
      "aggregate_per_metric_best": {
        "accuracy_at_accuracy_best_mean": 0.2547735124826431,
        "accuracy_at_accuracy_best_std": 0.0222268623176745,
        "top5_acc_at_accuracy_best_mean": 0.41873764991760254,
        "top5_acc_at_accuracy_best_std": 0.028793460731562862,
        "top10_acc_at_accuracy_best_mean": 0.4926503777503967,
        "top10_acc_at_accuracy_best_std": 0.026738932979739467,
        "mrr_at_accuracy_best_mean": 0.3368949592113495,
        "mrr_at_accuracy_best_std": 0.02514926566812927,
        "f1_at_accuracy_best_mean": 0.07358567118644714,
        "f1_at_accuracy_best_std": 0.0044140687920432645,
        "accuracy_at_top5_acc_best_mean": 0.24935615360736846,
        "accuracy_at_top5_acc_best_std": 0.02608740257019712,
        "top5_acc_at_top5_acc_best_mean": 0.42199567556381223,
        "top5_acc_at_top5_acc_best_std": 0.02721016327404005,
        "top10_acc_at_top5_acc_best_mean": 0.4924986660480499,
        "top10_acc_at_top5_acc_best_std": 0.027676414328433034,
        "mrr_at_top5_acc_best_mean": 0.3336707055568695,
        "mrr_at_top5_acc_best_std": 0.026441275552893825,
        "f1_at_top5_acc_best_mean": 0.06867484152317047,
        "f1_at_top5_acc_best_std": 0.004381574560778228,
        "accuracy_at_top10_acc_best_mean": 0.2465904802083969,
        "accuracy_at_top10_acc_best_std": 0.02393170412359417,
        "top5_acc_at_top10_acc_best_mean": 0.4197982847690582,
        "top5_acc_at_top10_acc_best_std": 0.02791676821334914,
        "top10_acc_at_top10_acc_best_mean": 0.49609783887863157,
        "top10_acc_at_top10_acc_best_std": 0.0275557356353355,
        "mrr_at_top10_acc_best_mean": 0.3319132447242737,
        "mrr_at_top10_acc_best_std": 0.02551137929198424,
        "f1_at_top10_acc_best_mean": 0.06589742600917817,
        "f1_at_top10_acc_best_std": 0.005545746012079228,
        "accuracy_at_mrr_best_mean": 0.2547735124826431,
        "accuracy_at_mrr_best_std": 0.0222268623176745,
        "top5_acc_at_mrr_best_mean": 0.41873764991760254,
        "top5_acc_at_mrr_best_std": 0.028793460731562862,
        "top10_acc_at_mrr_best_mean": 0.4926503777503967,
        "top10_acc_at_mrr_best_std": 0.026738932979739467,
        "mrr_at_mrr_best_mean": 0.3368949592113495,
        "mrr_at_mrr_best_std": 0.02514926566812927,
        "f1_at_mrr_best_mean": 0.07358567118644714,
        "f1_at_mrr_best_std": 0.0044140687920432645,
        "accuracy_at_f1_best_mean": 0.24909074902534484,
        "accuracy_at_f1_best_std": 0.024941966678388185,
        "top5_acc_at_f1_best_mean": 0.41585835814476013,
        "top5_acc_at_f1_best_std": 0.027194409360541606,
        "top10_acc_at_f1_best_mean": 0.4909076511859894,
        "top10_acc_at_f1_best_std": 0.02764980061398216,
        "mrr_at_f1_best_mean": 0.3325201451778412,
        "mrr_at_f1_best_std": 0.025962916549502668,
        "f1_at_f1_best_mean": 0.07569062858819961,
        "f1_at_f1_best_std": 0.0041444692151119305
      },
      "config": {
        "max_lr": 0.003,
        "label_smoothing": 0.0,
        "input_layernorm": false,
        "overrides": {
          "d_model": 256,
          "num_heads": 8,
          "transition_path": "output/check2hgi/arizona/region_transition_log_seed42_fold1.pt"
        },
        "input_type": "region"
      }
    }
  }
}