{
  "state": "alabama",
  "folds": 5,
  "epochs": 50,
  "seed": 42,
  "input_type": "region",
  "n_regions": 1109,
  "heads": {
    "next_stan_flow": {
      "per_fold": [
        {
          "accuracy": 0.16640441119670868,
          "accuracy_macro": 0.07821529323281101,
          "f1": 0.051957253366708755,
          "f1_weighted": 0.13930001854896545,
          "mrr": 0.28738686442375183,
          "top5_acc": 0.42564910650253296,
          "ndcg_5": 0.299515038728714,
          "top10_acc": 0.5479937195777893,
          "ndcg_10": 0.33943653106689453,
          "best_epoch": 16,
          "per_metric_best": {
            "accuracy": {
              "accuracy": 0.16640441119670868,
              "accuracy_macro": 0.07821529323281101,
              "f1": 0.051957253366708755,
              "f1_weighted": 0.13930001854896545,
              "mrr": 0.28738686442375183,
              "top5_acc": 0.42564910650253296,
              "ndcg_5": 0.299515038728714,
              "top10_acc": 0.5479937195777893,
              "ndcg_10": 0.33943653106689453,
              "best_epoch": 16
            },
            "top5_acc": {
              "accuracy": 0.15814319252967834,
              "accuracy_macro": 0.08240766286390595,
              "f1": 0.05311956629157066,
              "f1_weighted": 0.12907660007476807,
              "mrr": 0.2861708104610443,
              "top5_acc": 0.43312352895736694,
              "ndcg_5": 0.30165165662765503,
              "top10_acc": 0.5393391251564026,
              "ndcg_10": 0.33641573786735535,
              "best_epoch": 15
            },
            "top10_acc": {
              "accuracy": 0.16640441119670868,
              "accuracy_macro": 0.07821529323281101,
              "f1": 0.051957253366708755,
              "f1_weighted": 0.13930001854896545,
              "mrr": 0.28738686442375183,
              "top5_acc": 0.42564910650253296,
              "ndcg_5": 0.299515038728714,
              "top10_acc": 0.5479937195777893,
              "ndcg_10": 0.33943653106689453,
              "best_epoch": 16
            },
            "mrr": {
              "accuracy": 0.16640441119670868,
              "accuracy_macro": 0.07821529323281101,
              "f1": 0.051957253366708755,
              "f1_weighted": 0.13930001854896545,
              "mrr": 0.28738686442375183,
              "top5_acc": 0.42564910650253296,
              "ndcg_5": 0.299515038728714,
              "top10_acc": 0.5479937195777893,
              "ndcg_10": 0.33943653106689453,
              "best_epoch": 16
            },
            "f1": {
              "accuracy": 0.15420928597450256,
              "accuracy_macro": 0.07276914112246523,
              "f1": 0.05625835433602333,
              "f1_weighted": 0.15512715280056,
              "mrr": 0.27138349413871765,
              "top5_acc": 0.39535799622535706,
              "ndcg_5": 0.277497261762619,
              "top10_acc": 0.5279307961463928,
              "ndcg_10": 0.3205319046974182,
              "best_epoch": 29
            }
          }
        },
        {
          "accuracy": 0.1553894579410553,
          "accuracy_macro": 0.06267081525989045,
          "f1": 0.04773100093007088,
          "f1_weighted": 0.13950230181217194,
          "mrr": 0.2774510383605957,
          "top5_acc": 0.40833988785743713,
          "ndcg_5": 0.28709807991981506,
          "top10_acc": 0.5369787812232971,
          "ndcg_10": 0.32881805300712585,
          "best_epoch": 17,
          "per_metric_best": {
            "accuracy": {
              "accuracy": 0.17348544299602509,
              "accuracy_macro": 0.06581685162972713,
              "f1": 0.05015858635306358,
              "f1_weighted": 0.15883561968803406,
              "mrr": 0.28607240319252014,
              "top5_acc": 0.407553106546402,
              "ndcg_5": 0.29414239525794983,
              "top10_acc": 0.5228166580200195,
              "ndcg_10": 0.3319449722766876,
              "best_epoch": 18
            },
            "top5_acc": {
              "accuracy": 0.16640441119670868,
              "accuracy_macro": 0.06599903469303262,
              "f1": 0.04810699447989464,
              "f1_weighted": 0.15012678503990173,
              "mrr": 0.2848239839076996,
              "top5_acc": 0.410306841135025,
              "ndcg_5": 0.2938462495803833,
              "top10_acc": 0.5298977494239807,
              "ndcg_10": 0.33260923624038696,
              "best_epoch": 16
            },
            "top10_acc": {
              "accuracy": 0.1553894579410553,
              "accuracy_macro": 0.06267081525989045,
              "f1": 0.04773100093007088,
              "f1_weighted": 0.13950230181217194,
              "mrr": 0.2774510383605957,
              "top5_acc": 0.40833988785743713,
              "ndcg_5": 0.28709807991981506,
              "top10_acc": 0.5369787812232971,
              "ndcg_10": 0.32881805300712585,
              "best_epoch": 17
            },
            "mrr": {
              "accuracy": 0.17348544299602509,
              "accuracy_macro": 0.06581685162972713,
              "f1": 0.05015858635306358,
              "f1_weighted": 0.15883561968803406,
              "mrr": 0.28607240319252014,
              "top5_acc": 0.407553106546402,
              "ndcg_5": 0.29414239525794983,
              "top10_acc": 0.5228166580200195,
              "ndcg_10": 0.3319449722766876,
              "best_epoch": 18
            },
            "f1": {
              "accuracy": 0.1695515364408493,
              "accuracy_macro": 0.06478515267372131,
              "f1": 0.05104752629995346,
              "f1_weighted": 0.15289130806922913,
              "mrr": 0.2811663746833801,
              "top5_acc": 0.4036191999912262,
              "ndcg_5": 0.2894347608089447,
              "top10_acc": 0.5212430953979492,
              "ndcg_10": 0.3273320496082306,
              "best_epoch": 15
            }
          }
        },
        {
          "accuracy": 0.13690008223056793,
          "accuracy_macro": 0.06629151768154568,
          "f1": 0.04819006472826004,
          "f1_weighted": 0.12006106972694397,
          "mrr": 0.26388663053512573,
          "top5_acc": 0.40794649720191956,
          "ndcg_5": 0.2761073410511017,
          "top10_acc": 0.5444532036781311,
          "ndcg_10": 0.3203902542591095,
          "best_epoch": 21,
          "per_metric_best": {
            "accuracy": {
              "accuracy": 0.15656962990760803,
              "accuracy_macro": 0.08126013102522385,
              "f1": 0.05471448600292206,
              "f1_weighted": 0.13744741678237915,
              "mrr": 0.2784140706062317,
              "top5_acc": 0.4055861532688141,
              "ndcg_5": 0.2861402630805969,
              "top10_acc": 0.538945734500885,
              "ndcg_10": 0.32968100905418396,
              "best_epoch": 17
            },
            "top5_acc": {
              "accuracy": 0.15106216073036194,
              "accuracy_macro": 0.06626294655774637,
              "f1": 0.04807519167661667,
              "f1_weighted": 0.13867075741291046,
              "mrr": 0.27261993288993835,
              "top5_acc": 0.41542091965675354,
              "ndcg_5": 0.285957396030426,
              "top10_acc": 0.5322580933570862,
              "ndcg_10": 0.323782742023468,
              "best_epoch": 20
            },
            "top10_acc": {
              "accuracy": 0.13690008223056793,
              "accuracy_macro": 0.06629151768154568,
              "f1": 0.04819006472826004,
              "f1_weighted": 0.12006106972694397,
              "mrr": 0.26388663053512573,
              "top5_acc": 0.40794649720191956,
              "ndcg_5": 0.2761073410511017,
              "top10_acc": 0.5444532036781311,
              "ndcg_10": 0.3203902542591095,
              "best_epoch": 21
            },
            "mrr": {
              "accuracy": 0.15656962990760803,
              "accuracy_macro": 0.08126013102522385,
              "f1": 0.05471448600292206,
              "f1_weighted": 0.13744741678237915,
              "mrr": 0.2784140706062317,
              "top5_acc": 0.4055861532688141,
              "ndcg_5": 0.2861402630805969,
              "top10_acc": 0.538945734500885,
              "ndcg_10": 0.32968100905418396,
              "best_epoch": 17
            },
            "f1": {
              "accuracy": 0.15656962990760803,
              "accuracy_macro": 0.08126013102522385,
              "f1": 0.05471448600292206,
              "f1_weighted": 0.13744741678237915,
              "mrr": 0.2784140706062317,
              "top5_acc": 0.4055861532688141,
              "ndcg_5": 0.2861402630805969,
              "top10_acc": 0.538945734500885,
              "ndcg_10": 0.32968100905418396,
              "best_epoch": 17
            }
          }
        },
        {
          "accuracy": 0.14948859810829163,
          "accuracy_macro": 0.06506911320472832,
          "f1": 0.05106347054243088,
          "f1_weighted": 0.14899028837680817,
          "mrr": 0.2703700363636017,
          "top5_acc": 0.39221087098121643,
          "ndcg_5": 0.27670493721961975,
          "top10_acc": 0.5216364860534668,
          "ndcg_10": 0.3183959126472473,
          "best_epoch": 45,
          "per_metric_best": {
            "accuracy": {
              "accuracy": 0.18174666166305542,
              "accuracy_macro": 0.06309312558641621,
              "f1": 0.03933282941579819,
              "f1_weighted": 0.15403592586517334,
              "mrr": 0.29000744223594666,
              "top5_acc": 0.4055861532688141,
              "ndcg_5": 0.2972264289855957,
              "top10_acc": 0.5180959701538086,
              "ndcg_10": 0.3339838981628418,
              "best_epoch": 13
            },
            "top5_acc": {
              "accuracy": 0.18174666166305542,
              "accuracy_macro": 0.06309312558641621,
              "f1": 0.03933282941579819,
              "f1_weighted": 0.15403592586517334,
              "mrr": 0.29000744223594666,
              "top5_acc": 0.4055861532688141,
              "ndcg_5": 0.2972264289855957,
              "top10_acc": 0.5180959701538086,
              "ndcg_10": 0.3339838981628418,
              "best_epoch": 13
            },
            "top10_acc": {
              "accuracy": 0.14948859810829163,
              "accuracy_macro": 0.06506911320472832,
              "f1": 0.05106347054243088,
              "f1_weighted": 0.14899028837680817,
              "mrr": 0.2703700363636017,
              "top5_acc": 0.39221087098121643,
              "ndcg_5": 0.27670493721961975,
              "top10_acc": 0.5216364860534668,
              "ndcg_10": 0.3183959126472473,
              "best_epoch": 45
            },
            "mrr": {
              "accuracy": 0.18174666166305542,
              "accuracy_macro": 0.06309312558641621,
              "f1": 0.03933282941579819,
              "f1_weighted": 0.15403592586517334,
              "mrr": 0.29000744223594666,
              "top5_acc": 0.4055861532688141,
              "ndcg_5": 0.2972264289855957,
              "top10_acc": 0.5180959701538086,
              "ndcg_10": 0.3339838981628418,
              "best_epoch": 13
            },
            "f1": {
              "accuracy": 0.1534225046634674,
              "accuracy_macro": 0.0675593434606076,
              "f1": 0.051937274634838104,
              "f1_weighted": 0.14717766642570496,
              "mrr": 0.2717847526073456,
              "top5_acc": 0.392604261636734,
              "ndcg_5": 0.2779020369052887,
              "top10_acc": 0.517702579498291,
              "ndcg_10": 0.31834185123443604,
              "best_epoch": 42
            }
          }
        },
        {
          "accuracy": 0.1538764238357544,
          "accuracy_macro": 0.05650170767817516,
          "f1": 0.04160206392407417,
          "f1_weighted": 0.12986037135124207,
          "mrr": 0.24814650416374207,
          "top5_acc": 0.3337268829345703,
          "ndcg_5": 0.2470925897359848,
          "top10_acc": 0.44982290267944336,
          "ndcg_10": 0.2844593822956085,
          "best_epoch": 14,
          "per_metric_best": {
            "accuracy": {
              "accuracy": 0.1538764238357544,
              "accuracy_macro": 0.05650170767817516,
              "f1": 0.04160206392407417,
              "f1_weighted": 0.12986037135124207,
              "mrr": 0.24814650416374207,
              "top5_acc": 0.3337268829345703,
              "ndcg_5": 0.2470925897359848,
              "top10_acc": 0.44982290267944336,
              "ndcg_10": 0.2844593822956085,
              "best_epoch": 14
            },
            "top5_acc": {
              "accuracy": 0.1460055112838745,
              "accuracy_macro": 0.05710325941527631,
              "f1": 0.04164079576730728,
              "f1_weighted": 0.1288144290447235,
              "mrr": 0.24365027248859406,
              "top5_acc": 0.3419913351535797,
              "ndcg_5": 0.24771587550640106,
              "top10_acc": 0.43762296438217163,
              "ndcg_10": 0.2783692181110382,
              "best_epoch": 15
            },
            "top10_acc": {
              "accuracy": 0.1538764238357544,
              "accuracy_macro": 0.05650170767817516,
              "f1": 0.04160206392407417,
              "f1_weighted": 0.12986037135124207,
              "mrr": 0.24814650416374207,
              "top5_acc": 0.3337268829345703,
              "ndcg_5": 0.2470925897359848,
              "top10_acc": 0.44982290267944336,
              "ndcg_10": 0.2844593822956085,
              "best_epoch": 14
            },
            "mrr": {
              "accuracy": 0.1538764238357544,
              "accuracy_macro": 0.05650170767817516,
              "f1": 0.04160206392407417,
              "f1_weighted": 0.12986037135124207,
              "mrr": 0.24814650416374207,
              "top5_acc": 0.3337268829345703,
              "ndcg_5": 0.2470925897359848,
              "top10_acc": 0.44982290267944336,
              "ndcg_10": 0.2844593822956085,
              "best_epoch": 14
            },
            "f1": {
              "accuracy": 0.12278629839420319,
              "accuracy_macro": 0.05652146057221524,
              "f1": 0.04768459126353264,
              "f1_weighted": 0.12899363040924072,
              "mrr": 0.2261524200439453,
              "top5_acc": 0.32900431752204895,
              "ndcg_5": 0.22828157246112823,
              "top10_acc": 0.440377801656723,
              "ndcg_10": 0.2643100917339325,
              "best_epoch": 42
            }
          }
        }
      ],
      "aggregate": {
        "accuracy_mean": 0.1524117946624756,
        "accuracy_std": 0.010676647827788766,
        "top5_acc_mean": 0.3935746490955353,
        "top5_acc_std": 0.03548572993769783,
        "top10_acc_mean": 0.5201770186424255,
        "top10_acc_std": 0.0406116760140969,
        "mrr_mean": 0.2694482147693634,
        "mrr_std": 0.014759608614619833,
        "f1_mean": 0.04810877069830895,
        "f1_std": 0.004062869114948232
      },
      "aggregate_per_metric_best": {
        "accuracy_at_accuracy_best_mean": 0.1664165139198303,
        "accuracy_at_accuracy_best_std": 0.011610322117152764,
        "top5_acc_at_accuracy_best_mean": 0.3956202805042267,
        "top5_acc_at_accuracy_best_std": 0.035614437489678276,
        "top10_acc_at_accuracy_best_mean": 0.5155349969863892,
        "top10_acc_at_accuracy_best_std": 0.03866294030598283,
        "mrr_at_accuracy_best_mean": 0.27800545692443845,
        "mrr_at_accuracy_best_std": 0.01723991085594989,
        "f1_at_accuracy_best_mean": 0.04755304381251335,
        "f1_at_accuracy_best_std": 0.006716737569963183,
        "accuracy_at_top5_acc_best_mean": 0.16067238748073578,
        "accuracy_at_top5_acc_best_std": 0.01406104255434293,
        "top5_acc_at_top5_acc_best_mean": 0.40128575563430785,
        "top5_acc_at_top5_acc_best_std": 0.03474603709663681,
        "top10_acc_at_top5_acc_best_mean": 0.5114427804946899,
        "top10_acc_at_top5_acc_best_std": 0.04196933212701809,
        "mrr_at_top5_acc_best_mean": 0.2754544883966446,
        "mrr_at_top5_acc_best_std": 0.01893382109226087,
        "f1_at_top5_acc_best_mean": 0.046055075526237485,
        "f1_at_top5_acc_best_std": 0.005542398600477397,
        "accuracy_at_top10_acc_best_mean": 0.1524117946624756,
        "accuracy_at_top10_acc_best_std": 0.010676647827788766,
        "top5_acc_at_top10_acc_best_mean": 0.3935746490955353,
        "top5_acc_at_top10_acc_best_std": 0.03548572993769783,
        "top10_acc_at_top10_acc_best_mean": 0.5201770186424255,
        "top10_acc_at_top10_acc_best_std": 0.0406116760140969,
        "mrr_at_top10_acc_best_mean": 0.2694482147693634,
        "mrr_at_top10_acc_best_std": 0.014759608614619833,
        "f1_at_top10_acc_best_mean": 0.04810877069830895,
        "f1_at_top10_acc_best_std": 0.004062869114948232,
        "accuracy_at_mrr_best_mean": 0.1664165139198303,
        "accuracy_at_mrr_best_std": 0.011610322117152764,
        "top5_acc_at_mrr_best_mean": 0.3956202805042267,
        "top5_acc_at_mrr_best_std": 0.035614437489678276,
        "top10_acc_at_mrr_best_mean": 0.5155349969863892,
        "top10_acc_at_mrr_best_std": 0.03866294030598283,
        "mrr_at_mrr_best_mean": 0.27800545692443845,
        "mrr_at_mrr_best_std": 0.01723991085594989,
        "f1_at_mrr_best_mean": 0.04755304381251335,
        "f1_at_mrr_best_std": 0.006716737569963183,
        "accuracy_at_f1_best_mean": 0.1513078510761261,
        "accuracy_at_f1_best_std": 0.017225616272067912,
        "top5_acc_at_f1_best_mean": 0.38523438572883606,
        "top5_acc_at_f1_best_std": 0.03190148495127971,
        "top10_acc_at_f1_best_mean": 0.5092400014400482,
        "top10_acc_at_f1_best_std": 0.03933658740406015,
        "mrr_at_f1_best_mean": 0.2657802224159241,
        "mrr_at_f1_best_std": 0.022550840113756507,
        "f1_at_f1_best_mean": 0.05232844650745392,
        "f1_at_f1_best_std": 0.0033352857281419295
      },
      "config": {
        "max_lr": 0.003,
        "label_smoothing": 0.0,
        "input_layernorm": false,
        "overrides": {
          "freeze_alpha": "True",
          "alpha_init": 0.0
        },
        "input_type": "region"
      }
    }
  }
}