{
  "state": "alabama",
  "folds": 5,
  "epochs": 50,
  "seed": 42,
  "input_type": "checkin",
  "n_regions": 1109,
  "heads": {
    "next_gru": {
      "per_fold": [
        {
          "accuracy": 0.37765538692474365,
          "accuracy_macro": 0.1818249523639679,
          "f1": 0.1577584445476532,
          "f1_weighted": 0.29686906933784485,
          "mrr": 0.5961766242980957,
          "top5_acc": 0.905979573726654,
          "ndcg_5": 0.6628142595291138,
          "top10_acc": 1.0,
          "ndcg_10": 0.6953781843185425,
          "best_epoch": 1,
          "per_metric_best": {
            "accuracy": {
              "accuracy": 0.5692368149757385,
              "accuracy_macro": 0.49943211674690247,
              "f1": 0.5077747702598572,
              "f1_weighted": 0.5678628087043762,
              "mrr": 0.7291924357414246,
              "top5_acc": 0.9602674841880798,
              "ndcg_5": 0.7825770974159241,
              "top10_acc": 1.0,
              "ndcg_10": 0.7963611483573914,
              "best_epoch": 30
            },
            "top5_acc": {
              "accuracy": 0.5653029084205627,
              "accuracy_macro": 0.4936911165714264,
              "f1": 0.5066587924957275,
              "f1_weighted": 0.5621615052223206,
              "mrr": 0.7314572334289551,
              "top5_acc": 0.9701023101806641,
              "ndcg_5": 0.7880620360374451,
              "top10_acc": 1.0,
              "ndcg_10": 0.7984148859977722,
              "best_epoch": 25
            },
            "top10_acc": {
              "accuracy": 0.37765538692474365,
              "accuracy_macro": 0.1818249523639679,
              "f1": 0.1577584445476532,
              "f1_weighted": 0.29686906933784485,
              "mrr": 0.5961766242980957,
              "top5_acc": 0.905979573726654,
              "ndcg_5": 0.6628142595291138,
              "top10_acc": 1.0,
              "ndcg_10": 0.6953781843185425,
              "best_epoch": 1
            },
            "mrr": {
              "accuracy": 0.5653029084205627,
              "accuracy_macro": 0.4936911165714264,
              "f1": 0.5066587924957275,
              "f1_weighted": 0.5621615052223206,
              "mrr": 0.7314572334289551,
              "top5_acc": 0.9701023101806641,
              "ndcg_5": 0.7880620360374451,
              "top10_acc": 1.0,
              "ndcg_10": 0.7984148859977722,
              "best_epoch": 25
            },
            "f1": {
              "accuracy": 0.568843424320221,
              "accuracy_macro": 0.49584686756134033,
              "f1": 0.5113790035247803,
              "f1_weighted": 0.5662609338760376,
              "mrr": 0.7303426265716553,
              "top5_acc": 0.9626278877258301,
              "ndcg_5": 0.784389317035675,
              "top10_acc": 1.0,
              "ndcg_10": 0.7973416447639465,
              "best_epoch": 29
            }
          }
        },
        {
          "accuracy": 0.3788355588912964,
          "accuracy_macro": 0.1748737096786499,
          "f1": 0.13677352666854858,
          "f1_weighted": 0.2841007113456726,
          "mrr": 0.5987982749938965,
          "top5_acc": 0.9067663550376892,
          "ndcg_5": 0.6652593016624451,
          "top10_acc": 1.0,
          "ndcg_10": 0.6973720192909241,
          "best_epoch": 1,
          "per_metric_best": {
            "accuracy": {
              "accuracy": 0.5487805008888245,
              "accuracy_macro": 0.45030421018600464,
              "f1": 0.4783598780632019,
              "f1_weighted": 0.5416052937507629,
              "mrr": 0.7215026021003723,
              "top5_acc": 0.9575137495994568,
              "ndcg_5": 0.7761087417602539,
              "top10_acc": 1.0,
              "ndcg_10": 0.7908557057380676,
              "best_epoch": 25
            },
            "top5_acc": {
              "accuracy": 0.5118017196655273,
              "accuracy_macro": 0.3631742000579834,
              "f1": 0.39313507080078125,
              "f1_weighted": 0.48957887291908264,
              "mrr": 0.7015876770019531,
              "top5_acc": 0.9638080596923828,
              "ndcg_5": 0.7635546922683716,
              "top10_acc": 1.0,
              "ndcg_10": 0.7761135697364807,
              "best_epoch": 19
            },
            "top10_acc": {
              "accuracy": 0.3788355588912964,
              "accuracy_macro": 0.1748737096786499,
              "f1": 0.13677352666854858,
              "f1_weighted": 0.2841007113456726,
              "mrr": 0.5987982749938965,
              "top5_acc": 0.9067663550376892,
              "ndcg_5": 0.6652593016624451,
              "top10_acc": 1.0,
              "ndcg_10": 0.6973720192909241,
              "best_epoch": 1
            },
            "mrr": {
              "accuracy": 0.5487805008888245,
              "accuracy_macro": 0.45030421018600464,
              "f1": 0.4783598780632019,
              "f1_weighted": 0.5416052937507629,
              "mrr": 0.7215026021003723,
              "top5_acc": 0.9575137495994568,
              "ndcg_5": 0.7761087417602539,
              "top10_acc": 1.0,
              "ndcg_10": 0.7908557057380676,
              "best_epoch": 25
            },
            "f1": {
              "accuracy": 0.5448465943336487,
              "accuracy_macro": 0.45686253905296326,
              "f1": 0.4788550138473511,
              "f1_weighted": 0.5396251678466797,
              "mrr": 0.7188687324523926,
              "top5_acc": 0.9571203589439392,
              "ndcg_5": 0.7740607261657715,
              "top10_acc": 1.0,
              "ndcg_10": 0.7888489365577698,
              "best_epoch": 26
            }
          }
        },
        {
          "accuracy": 0.3768686056137085,
          "accuracy_macro": 0.18041831254959106,
          "f1": 0.1556151658296585,
          "f1_weighted": 0.29841628670692444,
          "mrr": 0.598556637763977,
          "top5_acc": 0.8988985419273376,
          "ndcg_5": 0.662294864654541,
          "top10_acc": 1.0,
          "ndcg_10": 0.6972551345825195,
          "best_epoch": 1,
          "per_metric_best": {
            "accuracy": {
              "accuracy": 0.5550747513771057,
              "accuracy_macro": 0.4817652404308319,
              "f1": 0.5106120109558105,
              "f1_weighted": 0.5513527393341064,
              "mrr": 0.7273697257041931,
              "top5_acc": 0.967348575592041,
              "ndcg_5": 0.7841034531593323,
              "top10_acc": 1.0,
              "ndcg_10": 0.7954281568527222,
              "best_epoch": 24
            },
            "top5_acc": {
              "accuracy": 0.48977184295654297,
              "accuracy_macro": 0.40347158908843994,
              "f1": 0.42715558409690857,
              "f1_weighted": 0.4789440631866455,
              "mrr": 0.6933882832527161,
              "top5_acc": 0.9712824821472168,
              "ndcg_5": 0.7603884935379028,
              "top10_acc": 1.0,
              "ndcg_10": 0.7703570127487183,
              "best_epoch": 18
            },
            "top10_acc": {
              "accuracy": 0.3768686056137085,
              "accuracy_macro": 0.18041831254959106,
              "f1": 0.1556151658296585,
              "f1_weighted": 0.29841628670692444,
              "mrr": 0.598556637763977,
              "top5_acc": 0.8988985419273376,
              "ndcg_5": 0.662294864654541,
              "top10_acc": 1.0,
              "ndcg_10": 0.6972551345825195,
              "best_epoch": 1
            },
            "mrr": {
              "accuracy": 0.5550747513771057,
              "accuracy_macro": 0.4817652404308319,
              "f1": 0.5106120109558105,
              "f1_weighted": 0.5513527393341064,
              "mrr": 0.7273697257041931,
              "top5_acc": 0.967348575592041,
              "ndcg_5": 0.7841034531593323,
              "top10_acc": 1.0,
              "ndcg_10": 0.7954281568527222,
              "best_epoch": 24
            },
            "f1": {
              "accuracy": 0.5452399849891663,
              "accuracy_macro": 0.49171268939971924,
              "f1": 0.5158944129943848,
              "f1_weighted": 0.5433122515678406,
              "mrr": 0.7156757116317749,
              "top5_acc": 0.9634146690368652,
              "ndcg_5": 0.7736484408378601,
              "top10_acc": 1.0,
              "ndcg_10": 0.7863205075263977,
              "best_epoch": 31
            }
          }
        },
        {
          "accuracy": 0.3977183401584625,
          "accuracy_macro": 0.1952333152294159,
          "f1": 0.17490825057029724,
          "f1_weighted": 0.3262527287006378,
          "mrr": 0.6104894876480103,
          "top5_acc": 0.9075531363487244,
          "ndcg_5": 0.6742008924484253,
          "top10_acc": 1.0,
          "ndcg_10": 0.7062042951583862,
          "best_epoch": 1,
          "per_metric_best": {
            "accuracy": {
              "accuracy": 0.5468135476112366,
              "accuracy_macro": 0.44052720069885254,
              "f1": 0.4678111970424652,
              "f1_weighted": 0.5376458168029785,
              "mrr": 0.7221413850784302,
              "top5_acc": 0.964594841003418,
              "ndcg_5": 0.779201865196228,
              "top10_acc": 1.0,
              "ndcg_10": 0.7914984822273254,
              "best_epoch": 25
            },
            "top5_acc": {
              "accuracy": 0.4701022803783417,
              "accuracy_macro": 0.3507995009422302,
              "f1": 0.37102699279785156,
              "f1_weighted": 0.45871230959892273,
              "mrr": 0.6766279339790344,
              "top5_acc": 0.9677419662475586,
              "ndcg_5": 0.7463721632957458,
              "top10_acc": 1.0,
              "ndcg_10": 0.757574737071991,
              "best_epoch": 15
            },
            "top10_acc": {
              "accuracy": 0.3977183401584625,
              "accuracy_macro": 0.1952333152294159,
              "f1": 0.17490825057029724,
              "f1_weighted": 0.3262527287006378,
              "mrr": 0.6104894876480103,
              "top5_acc": 0.9075531363487244,
              "ndcg_5": 0.6742008924484253,
              "top10_acc": 1.0,
              "ndcg_10": 0.7062042951583862,
              "best_epoch": 1
            },
            "mrr": {
              "accuracy": 0.543666422367096,
              "accuracy_macro": 0.4243764877319336,
              "f1": 0.4581097960472107,
              "f1_weighted": 0.5293185710906982,
              "mrr": 0.7231454253196716,
              "top5_acc": 0.9622344970703125,
              "ndcg_5": 0.779256284236908,
              "top10_acc": 1.0,
              "ndcg_10": 0.7923756837844849,
              "best_epoch": 23
            },
            "f1": {
              "accuracy": 0.5369787812232971,
              "accuracy_macro": 0.44728586077690125,
              "f1": 0.4728321135044098,
              "f1_weighted": 0.5303345322608948,
              "mrr": 0.7157506942749023,
              "top5_acc": 0.9618411064147949,
              "ndcg_5": 0.7734254598617554,
              "top10_acc": 1.0,
              "ndcg_10": 0.786666989326477,
              "best_epoch": 27
            }
          }
        },
        {
          "accuracy": 0.37622982263565063,
          "accuracy_macro": 0.19104641675949097,
          "f1": 0.17320995032787323,
          "f1_weighted": 0.3101617097854614,
          "mrr": 0.5970867872238159,
          "top5_acc": 0.9079102277755737,
          "ndcg_5": 0.6643426418304443,
          "top10_acc": 1.0,
          "ndcg_10": 0.6960924863815308,
          "best_epoch": 1,
          "per_metric_best": {
            "accuracy": {
              "accuracy": 0.5143644213676453,
              "accuracy_macro": 0.45001691579818726,
              "f1": 0.47336697578430176,
              "f1_weighted": 0.5090910196304321,
              "mrr": 0.7019293308258057,
              "top5_acc": 0.9610389471054077,
              "ndcg_5": 0.7627385258674622,
              "top10_acc": 1.0,
              "ndcg_10": 0.7762836813926697,
              "best_epoch": 26
            },
            "top5_acc": {
              "accuracy": 0.4765840172767639,
              "accuracy_macro": 0.3933377265930176,
              "f1": 0.4143977761268616,
              "f1_weighted": 0.4694690704345703,
              "mrr": 0.6825509071350098,
              "top5_acc": 0.9661550521850586,
              "ndcg_5": 0.7503258585929871,
              "top10_acc": 1.0,
              "ndcg_10": 0.7621025443077087,
              "best_epoch": 19
            },
            "top10_acc": {
              "accuracy": 0.37622982263565063,
              "accuracy_macro": 0.19104641675949097,
              "f1": 0.17320995032787323,
              "f1_weighted": 0.3101617097854614,
              "mrr": 0.5970867872238159,
              "top5_acc": 0.9079102277755737,
              "ndcg_5": 0.6643426418304443,
              "top10_acc": 1.0,
              "ndcg_10": 0.6960924863815308,
              "best_epoch": 1
            },
            "mrr": {
              "accuracy": 0.5143644213676453,
              "accuracy_macro": 0.45001691579818726,
              "f1": 0.47336697578430176,
              "f1_weighted": 0.5090910196304321,
              "mrr": 0.7019293308258057,
              "top5_acc": 0.9610389471054077,
              "ndcg_5": 0.7627385258674622,
              "top10_acc": 1.0,
              "ndcg_10": 0.7762836813926697,
              "best_epoch": 26
            },
            "f1": {
              "accuracy": 0.5080676674842834,
              "accuracy_macro": 0.4683207869529724,
              "f1": 0.4802629351615906,
              "f1_weighted": 0.5070723295211792,
              "mrr": 0.6981868743896484,
              "top5_acc": 0.9578905701637268,
              "ndcg_5": 0.7588725090026855,
              "top10_acc": 1.0,
              "ndcg_10": 0.7734851241111755,
              "best_epoch": 27
            }
          }
        }
      ],
      "aggregate": {
        "accuracy_mean": 0.38146154284477235,
        "accuracy_std": 0.009139639520584386,
        "top5_acc_mean": 0.9054215669631958,
        "top5_acc_std": 0.003721783941075345,
        "top10_acc_mean": 1.0,
        "top10_acc_std": 0.0,
        "mrr_mean": 0.6002215623855591,
        "mrr_std": 0.005839870495914112,
        "f1_mean": 0.15965306758880615,
        "f1_std": 0.015490943460663766
      },
      "aggregate_per_metric_best": {
        "accuracy_at_accuracy_best_mean": 0.5468540072441102,
        "accuracy_at_accuracy_best_std": 0.020173354463378344,
        "top5_acc_at_accuracy_best_mean": 0.9621527194976807,
        "top5_acc_at_accuracy_best_std": 0.0038495298684731827,
        "top10_acc_at_accuracy_best_mean": 1.0,
        "top10_acc_at_accuracy_best_std": 0.0,
        "mrr_at_accuracy_best_mean": 0.7204270958900452,
        "mrr_at_accuracy_best_std": 0.010854654587412502,
        "f1_at_accuracy_best_mean": 0.4875849664211273,
        "f1_at_accuracy_best_std": 0.0201005499144276,
        "accuracy_at_top5_acc_best_mean": 0.5027125537395477,
        "accuracy_at_top5_acc_best_std": 0.03845048042051696,
        "top5_acc_at_top5_acc_best_mean": 0.9678179740905761,
        "top5_acc_at_top5_acc_best_std": 0.0030029779962519976,
        "top10_acc_at_top5_acc_best_mean": 1.0,
        "top10_acc_at_top5_acc_best_std": 0.0,
        "mrr_at_top5_acc_best_mean": 0.6971224069595336,
        "mrr_at_top5_acc_best_std": 0.02147739890547352,
        "f1_at_top5_acc_best_mean": 0.4224748432636261,
        "f1_at_top5_acc_best_std": 0.05167637086307774,
        "accuracy_at_top10_acc_best_mean": 0.38146154284477235,
        "accuracy_at_top10_acc_best_std": 0.009139639520584386,
        "top5_acc_at_top10_acc_best_mean": 0.9054215669631958,
        "top5_acc_at_top10_acc_best_std": 0.003721783941075345,
        "top10_acc_at_top10_acc_best_mean": 1.0,
        "top10_acc_at_top10_acc_best_std": 0.0,
        "mrr_at_top10_acc_best_mean": 0.6002215623855591,
        "mrr_at_top10_acc_best_std": 0.005839870495914112,
        "f1_at_top10_acc_best_mean": 0.15965306758880615,
        "f1_at_top10_acc_best_std": 0.015490943460663766,
        "accuracy_at_mrr_best_mean": 0.5454378008842469,
        "accuracy_at_mrr_best_std": 0.019153065368144005,
        "top5_acc_at_mrr_best_mean": 0.9636476159095764,
        "top5_acc_at_mrr_best_std": 0.005044466136237468,
        "top10_acc_at_mrr_best_mean": 1.0,
        "top10_acc_at_mrr_best_std": 0.0,
        "mrr_at_mrr_best_mean": 0.7210808634757996,
        "mrr_at_mrr_best_std": 0.011384642324760087,
        "f1_at_mrr_best_mean": 0.4854214906692505,
        "f1_at_mrr_best_std": 0.022509396182557803,
        "accuracy_at_f1_best_mean": 0.5407952904701233,
        "accuracy_at_f1_best_std": 0.02184335845268306,
        "top5_acc_at_f1_best_mean": 0.9605789184570312,
        "top5_acc_at_f1_best_std": 0.0028732266403795393,
        "top10_acc_at_f1_best_mean": 1.0,
        "top10_acc_at_f1_best_std": 0.0,
        "mrr_at_f1_best_mean": 0.7157649278640748,
        "mrr_at_f1_best_std": 0.011523226855056868,
        "f1_at_f1_best_mean": 0.4918446958065033,
        "f1_at_f1_best_std": 0.020151460106399673
      },
      "config": {
        "max_lr": 0.003,
        "label_smoothing": 0.0,
        "input_layernorm": false,
        "overrides": {},
        "input_type": "checkin"
      }
    }
  }
}