{
  "state": "georgia",
  "folds": 5,
  "epochs": 50,
  "seed": 7,
  "input_type": "region",
  "n_regions": 2282,
  "heads": {
    "next_stan_flow": {
      "per_fold": [
        {
          "accuracy": 0.27445530891418457,
          "accuracy_macro": 0.09089160397575165,
          "f1": 0.07381779700517654,
          "f1_weighted": 0.23670047521591187,
          "mrr": 0.3782585561275482,
          "top5_acc": 0.49399733543395996,
          "ndcg_5": 0.38958847522735596,
          "top10_acc": 0.5864828824996948,
          "ndcg_10": 0.4194023907184601,
          "best_epoch": 42,
          "per_metric_best": {
            "accuracy": {
              "accuracy": 0.27667853236198425,
              "accuracy_macro": 0.09090125178742232,
              "f1": 0.07391718775033951,
              "f1_weighted": 0.23833119869232178,
              "mrr": 0.3791300356388092,
              "top5_acc": 0.4926634132862091,
              "ndcg_5": 0.38973817229270935,
              "top10_acc": 0.5850377678871155,
              "ndcg_10": 0.4196144938468933,
              "best_epoch": 44
            },
            "top5_acc": {
              "accuracy": 0.27445530891418457,
              "accuracy_macro": 0.09089160397575165,
              "f1": 0.07381779700517654,
              "f1_weighted": 0.23670047521591187,
              "mrr": 0.3782585561275482,
              "top5_acc": 0.49399733543395996,
              "ndcg_5": 0.38958847522735596,
              "top10_acc": 0.5864828824996948,
              "ndcg_10": 0.4194023907184601,
              "best_epoch": 42
            },
            "top10_acc": {
              "accuracy": 0.27445530891418457,
              "accuracy_macro": 0.09089160397575165,
              "f1": 0.07381779700517654,
              "f1_weighted": 0.23670047521591187,
              "mrr": 0.3782585561275482,
              "top5_acc": 0.49399733543395996,
              "ndcg_5": 0.38958847522735596,
              "top10_acc": 0.5864828824996948,
              "ndcg_10": 0.4194023907184601,
              "best_epoch": 42
            },
            "mrr": {
              "accuracy": 0.27667853236198425,
              "accuracy_macro": 0.09090125178742232,
              "f1": 0.07391718775033951,
              "f1_weighted": 0.23833119869232178,
              "mrr": 0.3791300356388092,
              "top5_acc": 0.4926634132862091,
              "ndcg_5": 0.38973817229270935,
              "top10_acc": 0.5850377678871155,
              "ndcg_10": 0.4196144938468933,
              "best_epoch": 44
            },
            "f1": {
              "accuracy": 0.2733437120914459,
              "accuracy_macro": 0.09249977689040334,
              "f1": 0.07581564038991928,
              "f1_weighted": 0.23590901494026184,
              "mrr": 0.37596333026885986,
              "top5_acc": 0.48877277970314026,
              "ndcg_5": 0.3862476050853729,
              "top10_acc": 0.5827034115791321,
              "ndcg_10": 0.4164943993091583,
              "best_epoch": 38
            }
          }
        },
        {
          "accuracy": 0.27445530891418457,
          "accuracy_macro": 0.09153723797011455,
          "f1": 0.0755033865571022,
          "f1_weighted": 0.23856091499328613,
          "mrr": 0.37182846665382385,
          "top5_acc": 0.4753223657608032,
          "ndcg_5": 0.37929877638816833,
          "top10_acc": 0.5738105773925781,
          "ndcg_10": 0.41115355491638184,
          "best_epoch": 39,
          "per_metric_best": {
            "accuracy": {
              "accuracy": 0.274899959564209,
              "accuracy_macro": 0.09057823492556202,
              "f1": 0.07386037707328796,
              "f1_weighted": 0.23448120057582855,
              "mrr": 0.37231412529945374,
              "top5_acc": 0.47576701641082764,
              "ndcg_5": 0.3798125386238098,
              "top10_acc": 0.5710315704345703,
              "ndcg_10": 0.4106908142566681,
              "best_epoch": 34
            },
            "top5_acc": {
              "accuracy": 0.27389952540397644,
              "accuracy_macro": 0.09211661657232312,
              "f1": 0.07661926001310349,
              "f1_weighted": 0.23779171705245972,
              "mrr": 0.37234827876091003,
              "top5_acc": 0.4793241322040558,
              "ndcg_5": 0.3810080885887146,
              "top10_acc": 0.5713650584220886,
              "ndcg_10": 0.41079527139663696,
              "best_epoch": 43
            },
            "top10_acc": {
              "accuracy": 0.27445530891418457,
              "accuracy_macro": 0.09153723797011455,
              "f1": 0.0755033865571022,
              "f1_weighted": 0.23856091499328613,
              "mrr": 0.37182846665382385,
              "top5_acc": 0.4753223657608032,
              "ndcg_5": 0.37929877638816833,
              "top10_acc": 0.5738105773925781,
              "ndcg_10": 0.41115355491638184,
              "best_epoch": 39
            },
            "mrr": {
              "accuracy": 0.27412182092666626,
              "accuracy_macro": 0.09080835012443961,
              "f1": 0.07589417695999146,
              "f1_weighted": 0.2382749617099762,
              "mrr": 0.37278634309768677,
              "top5_acc": 0.4774344265460968,
              "ndcg_5": 0.38066375255584717,
              "top10_acc": 0.5714762210845947,
              "ndcg_10": 0.411188006401062,
              "best_epoch": 45
            },
            "f1": {
              "accuracy": 0.2732325494289398,
              "accuracy_macro": 0.09237790853414915,
              "f1": 0.07701230049133301,
              "f1_weighted": 0.23625019192695618,
              "mrr": 0.37151241302490234,
              "top5_acc": 0.47387728095054626,
              "ndcg_5": 0.3785664141178131,
              "top10_acc": 0.569586455821991,
              "ndcg_10": 0.4096634089946747,
              "best_epoch": 41
            }
          }
        },
        {
          "accuracy": 0.2698165476322174,
          "accuracy_macro": 0.08806112086519281,
          "f1": 0.07154036313295364,
          "f1_weighted": 0.23484331369400024,
          "mrr": 0.3688456118106842,
          "top5_acc": 0.4737076163291931,
          "ndcg_5": 0.3774575889110565,
          "top10_acc": 0.5632017850875854,
          "ndcg_10": 0.4063641130924225,
          "best_epoch": 39,
          "per_metric_best": {
            "accuracy": {
              "accuracy": 0.2712618112564087,
              "accuracy_macro": 0.08908384937351033,
              "f1": 0.07282799482345581,
              "f1_weighted": 0.23683567345142365,
              "mrr": 0.3694871962070465,
              "top5_acc": 0.4753752052783966,
              "ndcg_5": 0.3785414397716522,
              "top10_acc": 0.5629794001579285,
              "ndcg_10": 0.4067721366882324,
              "best_epoch": 40
            },
            "top5_acc": {
              "accuracy": 0.2699277400970459,
              "accuracy_macro": 0.08938589573310936,
              "f1": 0.07343665510416031,
              "f1_weighted": 0.23728471994400024,
              "mrr": 0.36926335096359253,
              "top5_acc": 0.4758198857307434,
              "ndcg_5": 0.3785092234611511,
              "top10_acc": 0.5610894560813904,
              "ndcg_10": 0.40612226724624634,
              "best_epoch": 48
            },
            "top10_acc": {
              "accuracy": 0.2698165476322174,
              "accuracy_macro": 0.08806112086519281,
              "f1": 0.07154036313295364,
              "f1_weighted": 0.23484331369400024,
              "mrr": 0.3688456118106842,
              "top5_acc": 0.4737076163291931,
              "ndcg_5": 0.3774575889110565,
              "top10_acc": 0.5632017850875854,
              "ndcg_10": 0.4063641130924225,
              "best_epoch": 39
            },
            "mrr": {
              "accuracy": 0.2712618112564087,
              "accuracy_macro": 0.08908384937351033,
              "f1": 0.07282799482345581,
              "f1_weighted": 0.23683567345142365,
              "mrr": 0.3694871962070465,
              "top5_acc": 0.4753752052783966,
              "ndcg_5": 0.3785414397716522,
              "top10_acc": 0.5629794001579285,
              "ndcg_10": 0.4067721366882324,
              "best_epoch": 40
            },
            "f1": {
              "accuracy": 0.2695942223072052,
              "accuracy_macro": 0.08935957489272735,
              "f1": 0.07400138676166534,
              "f1_weighted": 0.23713228106498718,
              "mrr": 0.36896181106567383,
              "top5_acc": 0.475152850151062,
              "ndcg_5": 0.37807124853134155,
              "top10_acc": 0.5608671307563782,
              "ndcg_10": 0.4058508574962616,
              "best_epoch": 45
            }
          }
        },
        {
          "accuracy": 0.30850473046302795,
          "accuracy_macro": 0.09186439682208494,
          "f1": 0.07416898012161255,
          "f1_weighted": 0.2674298882484436,
          "mrr": 0.4140041470527649,
          "top5_acc": 0.5310727953910828,
          "ndcg_5": 0.4260580539703369,
          "top10_acc": 0.6219010353088379,
          "ndcg_10": 0.45543941855430603,
          "best_epoch": 46,
          "per_metric_best": {
            "accuracy": {
              "accuracy": 0.30972760915756226,
              "accuracy_macro": 0.09414803718276829,
              "f1": 0.07459570467472076,
              "f1_weighted": 0.2669605016708374,
              "mrr": 0.4145515263080597,
              "top5_acc": 0.5328515768051147,
              "ndcg_5": 0.42714235186576843,
              "top10_acc": 0.620455801486969,
              "ndcg_10": 0.45547232031822205,
              "best_epoch": 42
            },
            "top5_acc": {
              "accuracy": 0.30972760915756226,
              "accuracy_macro": 0.09414803718276829,
              "f1": 0.07459570467472076,
              "f1_weighted": 0.2669605016708374,
              "mrr": 0.4145515263080597,
              "top5_acc": 0.5328515768051147,
              "ndcg_5": 0.42714235186576843,
              "top10_acc": 0.620455801486969,
              "ndcg_10": 0.45547232031822205,
              "best_epoch": 42
            },
            "top10_acc": {
              "accuracy": 0.30850473046302795,
              "accuracy_macro": 0.09186439682208494,
              "f1": 0.07416898012161255,
              "f1_weighted": 0.2674298882484436,
              "mrr": 0.4140041470527649,
              "top5_acc": 0.5310727953910828,
              "ndcg_5": 0.4260580539703369,
              "top10_acc": 0.6219010353088379,
              "ndcg_10": 0.45543941855430603,
              "best_epoch": 46
            },
            "mrr": {
              "accuracy": 0.30972760915756226,
              "accuracy_macro": 0.09414803718276829,
              "f1": 0.07459570467472076,
              "f1_weighted": 0.2669605016708374,
              "mrr": 0.4145515263080597,
              "top5_acc": 0.5328515768051147,
              "ndcg_5": 0.42714235186576843,
              "top10_acc": 0.620455801486969,
              "ndcg_10": 0.45547232031822205,
              "best_epoch": 42
            },
            "f1": {
              "accuracy": 0.30761533975601196,
              "accuracy_macro": 0.09345035569842783,
              "f1": 0.07482222467660904,
              "f1_weighted": 0.266366183757782,
              "mrr": 0.4129991829395294,
              "top5_acc": 0.5290716886520386,
              "ndcg_5": 0.42459753155708313,
              "top10_acc": 0.6205669641494751,
              "ndcg_10": 0.45426496863365173,
              "best_epoch": 43
            }
          }
        },
        {
          "accuracy": 0.2754557728767395,
          "accuracy_macro": 0.07980778188884156,
          "f1": 0.06663846969604492,
          "f1_weighted": 0.24013841152191162,
          "mrr": 0.37635329365730286,
          "top5_acc": 0.48621609807014465,
          "ndcg_5": 0.3864836096763611,
          "top10_acc": 0.5764784216880798,
          "ndcg_10": 0.41567492485046387,
          "best_epoch": 32,
          "per_metric_best": {
            "accuracy": {
              "accuracy": 0.28156960010528564,
              "accuracy_macro": 0.08653267049222729,
              "f1": 0.07235285639762878,
              "f1_weighted": 0.24847100675106049,
              "mrr": 0.38063520193099976,
              "top5_acc": 0.48643842339515686,
              "ndcg_5": 0.38959819078445435,
              "top10_acc": 0.5753668546676636,
              "ndcg_10": 0.41851356625556946,
              "best_epoch": 43
            },
            "top5_acc": {
              "accuracy": 0.2784571051597595,
              "accuracy_macro": 0.08231614087079023,
              "f1": 0.06831858307123184,
              "f1_weighted": 0.24248354136943817,
              "mrr": 0.37903842329978943,
              "top5_acc": 0.4904401898384094,
              "ndcg_5": 0.3898388743400574,
              "top10_acc": 0.5761449337005615,
              "ndcg_10": 0.41758111119270325,
              "best_epoch": 37
            },
            "top10_acc": {
              "accuracy": 0.2754557728767395,
              "accuracy_macro": 0.07980778188884156,
              "f1": 0.06663846969604492,
              "f1_weighted": 0.24013841152191162,
              "mrr": 0.37635329365730286,
              "top5_acc": 0.48621609807014465,
              "ndcg_5": 0.3864836096763611,
              "top10_acc": 0.5764784216880798,
              "ndcg_10": 0.41567492485046387,
              "best_epoch": 32
            },
            "mrr": {
              "accuracy": 0.28112494945526123,
              "accuracy_macro": 0.0859232636403997,
              "f1": 0.07136736810207367,
              "f1_weighted": 0.2460642158985138,
              "mrr": 0.3808104693889618,
              "top5_acc": 0.4896620810031891,
              "ndcg_5": 0.39095959067344666,
              "top10_acc": 0.5748110413551331,
              "ndcg_10": 0.418593168258667,
              "best_epoch": 42
            },
            "f1": {
              "accuracy": 0.28156960010528564,
              "accuracy_macro": 0.08653267049222729,
              "f1": 0.07235285639762878,
              "f1_weighted": 0.24847100675106049,
              "mrr": 0.38063520193099976,
              "top5_acc": 0.48643842339515686,
              "ndcg_5": 0.38959819078445435,
              "top10_acc": 0.5753668546676636,
              "ndcg_10": 0.41851356625556946,
              "best_epoch": 43
            }
          }
        }
      ],
      "aggregate": {
        "accuracy_mean": 0.2805375337600708,
        "accuracy_std": 0.015786979182246284,
        "top5_acc_mean": 0.49206324219703673,
        "top5_acc_std": 0.02332842148722431,
        "top10_acc_mean": 0.5843749403953552,
        "top10_acc_std": 0.022555013291986177,
        "mrr_mean": 0.3818580150604248,
        "mrr_std": 0.01834765886958481,
        "f1_mean": 0.07233379930257797,
        "f1_std": 0.0034886509379068275
      },
      "aggregate_per_metric_best": {
        "accuracy_at_accuracy_best_mean": 0.28282750248908994,
        "accuracy_at_accuracy_best_std": 0.015488859232703012,
        "top5_acc_at_accuracy_best_mean": 0.492619127035141,
        "top5_acc_at_accuracy_best_std": 0.023654806822808898,
        "top10_acc_at_accuracy_best_mean": 0.5829742789268494,
        "top10_acc_at_accuracy_best_std": 0.022413271108254945,
        "mrr_at_accuracy_best_mean": 0.3832236170768738,
        "mrr_at_accuracy_best_std": 0.018114921114301755,
        "f1_at_accuracy_best_mean": 0.07351082414388657,
        "f1_at_accuracy_best_std": 0.0009043546842222477,
        "accuracy_at_top5_acc_best_mean": 0.2812934577465057,
        "accuracy_at_top5_acc_best_std": 0.01617989427568478,
        "top5_acc_at_top5_acc_best_mean": 0.4944866240024567,
        "top5_acc_at_top5_acc_best_std": 0.02273120603673852,
        "top10_acc_at_top5_acc_best_mean": 0.5831076264381408,
        "top10_acc_at_top5_acc_best_std": 0.022789500612054904,
        "mrr_at_top5_acc_best_mean": 0.38269202709197997,
        "mrr_at_top5_acc_best_std": 0.018271252337071667,
        "f1_at_top5_acc_best_mean": 0.07335759997367859,
        "f1_at_top5_acc_best_std": 0.0030733146531116435,
        "accuracy_at_top10_acc_best_mean": 0.2805375337600708,
        "accuracy_at_top10_acc_best_std": 0.015786979182246284,
        "top5_acc_at_top10_acc_best_mean": 0.49206324219703673,
        "top5_acc_at_top10_acc_best_std": 0.02332842148722431,
        "top10_acc_at_top10_acc_best_mean": 0.5843749403953552,
        "top10_acc_at_top10_acc_best_std": 0.022555013291986177,
        "mrr_at_top10_acc_best_mean": 0.3818580150604248,
        "mrr_at_top10_acc_best_std": 0.01834765886958481,
        "f1_at_top10_acc_best_mean": 0.07233379930257797,
        "f1_at_top10_acc_best_std": 0.0034886509379068275,
        "accuracy_at_mrr_best_mean": 0.2825829446315765,
        "accuracy_at_mrr_best_std": 0.015601116319513102,
        "top5_acc_at_mrr_best_mean": 0.4935973405838013,
        "top5_acc_at_mrr_best_std": 0.023186955140559993,
        "top10_acc_at_mrr_best_mean": 0.5829520463943482,
        "top10_acc_at_mrr_best_std": 0.022404011959168985,
        "mrr_at_mrr_best_mean": 0.3833531141281128,
        "mrr_at_mrr_best_std": 0.01803857454560509,
        "f1_at_mrr_best_mean": 0.07372048646211624,
        "f1_at_mrr_best_std": 0.0017221596934129373,
        "accuracy_at_f1_best_mean": 0.2810710847377777,
        "accuracy_at_f1_best_std": 0.015473520018875453,
        "top5_acc_at_f1_best_mean": 0.4906626045703888,
        "top5_acc_at_f1_best_std": 0.022466488687554,
        "top10_acc_at_f1_best_mean": 0.581818163394928,
        "top10_acc_at_f1_best_std": 0.02308913731243076,
        "mrr_at_f1_best_mean": 0.38201438784599306,
        "mrr_at_f1_best_std": 0.017883205908947673,
        "f1_at_f1_best_mean": 0.0748008817434311,
        "f1_at_f1_best_std": 0.0017714812890311867
      },
      "config": {
        "max_lr": 0.003,
        "label_smoothing": 0.0,
        "input_layernorm": false,
        "overrides": {
          "freeze_alpha": "True",
          "alpha_init": 0.0
        },
        "input_type": "region"
      }
    }
  }
}