{
  "state": "florida",
  "folds": 5,
  "epochs": 50,
  "seed": 42,
  "input_type": "region",
  "n_regions": 4702,
  "heads": {
    "next_tgstan": {
      "per_fold": [
        {
          "accuracy": 0.47369247674942017,
          "accuracy_macro": 0.12320374571000939,
          "f1": 0.1106167882680893,
          "f1_weighted": 0.4501926004886627,
          "mrr": 0.5616514086723328,
          "top5_acc": 0.6633265018463135,
          "ndcg_5": 0.5751008987426758,
          "top10_acc": 0.7293545007705688,
          "ndcg_10": 0.5965132117271423,
          "best_epoch": 48,
          "per_metric_best": {
            "accuracy": {
              "accuracy": 0.4748547077178955,
              "accuracy_macro": 0.12333007412924508,
              "f1": 0.1102498322725296,
              "f1_weighted": 0.44983887672424316,
              "mrr": 0.5614707469940186,
              "top5_acc": 0.6613475680351257,
              "ndcg_5": 0.5743862390518188,
              "top10_acc": 0.727658212184906,
              "ndcg_10": 0.5958774089813232,
              "best_epoch": 35
            },
            "top5_acc": {
              "accuracy": 0.47356683015823364,
              "accuracy_macro": 0.12329316123628087,
              "f1": 0.11051865667104721,
              "f1_weighted": 0.4500095248222351,
              "mrr": 0.5615103840827942,
              "top5_acc": 0.6634835600852966,
              "ndcg_5": 0.5750590562820435,
              "top10_acc": 0.7291032075881958,
              "ndcg_10": 0.5963282585144043,
              "best_epoch": 47
            },
            "top10_acc": {
              "accuracy": 0.47369247674942017,
              "accuracy_macro": 0.12320374571000939,
              "f1": 0.1106167882680893,
              "f1_weighted": 0.4501926004886627,
              "mrr": 0.5616514086723328,
              "top5_acc": 0.6633265018463135,
              "ndcg_5": 0.5751008987426758,
              "top10_acc": 0.7293545007705688,
              "ndcg_10": 0.5965132117271423,
              "best_epoch": 48
            },
            "mrr": {
              "accuracy": 0.4739123582839966,
              "accuracy_macro": 0.12362146657872713,
              "f1": 0.11076301336288452,
              "f1_weighted": 0.4502471685409546,
              "mrr": 0.5618484616279602,
              "top5_acc": 0.6630437970161438,
              "ndcg_5": 0.5751392245292664,
              "top10_acc": 0.729260265827179,
              "ndcg_10": 0.5966314077377319,
              "best_epoch": 49
            },
            "f1": {
              "accuracy": 0.4734411835670471,
              "accuracy_macro": 0.125840576971026,
              "f1": 0.11265911161899567,
              "f1_weighted": 0.4498564600944519,
              "mrr": 0.5612658262252808,
              "top5_acc": 0.6632636785507202,
              "ndcg_5": 0.5748006105422974,
              "top10_acc": 0.7285692095756531,
              "ndcg_10": 0.5959977507591248,
              "best_epoch": 39
            }
          }
        },
        {
          "accuracy": 0.4623841643333435,
          "accuracy_macro": 0.0994946656065831,
          "f1": 0.08927584439516068,
          "f1_weighted": 0.4353185296058655,
          "mrr": 0.5489277839660645,
          "top5_acc": 0.6455159187316895,
          "ndcg_5": 0.5605289936065674,
          "top10_acc": 0.7145280241966248,
          "ndcg_10": 0.5828808546066284,
          "best_epoch": 35,
          "per_metric_best": {
            "accuracy": {
              "accuracy": 0.46354642510414124,
              "accuracy_macro": 0.1010378183906943,
              "f1": 0.09104104340076447,
              "f1_weighted": 0.43813997507095337,
              "mrr": 0.549412727355957,
              "top5_acc": 0.6464583277702332,
              "ndcg_5": 0.5611766576766968,
              "top10_acc": 0.7138369679450989,
              "ndcg_10": 0.5830317139625549,
              "best_epoch": 43
            },
            "top5_acc": {
              "accuracy": 0.4621642827987671,
              "accuracy_macro": 0.09914350802581058,
              "f1": 0.08951088786125183,
              "f1_weighted": 0.4370429813861847,
              "mrr": 0.5490266680717468,
              "top5_acc": 0.6476833820343018,
              "ndcg_5": 0.5613449811935425,
              "top10_acc": 0.7133657932281494,
              "ndcg_10": 0.5826322436332703,
              "best_epoch": 42
            },
            "top10_acc": {
              "accuracy": 0.4623841643333435,
              "accuracy_macro": 0.0994946656065831,
              "f1": 0.08927584439516068,
              "f1_weighted": 0.4353185296058655,
              "mrr": 0.5489277839660645,
              "top5_acc": 0.6455159187316895,
              "ndcg_5": 0.5605289936065674,
              "top10_acc": 0.7145280241966248,
              "ndcg_10": 0.5828808546066284,
              "best_epoch": 35
            },
            "mrr": {
              "accuracy": 0.46354642510414124,
              "accuracy_macro": 0.1010378183906943,
              "f1": 0.09104104340076447,
              "f1_weighted": 0.43813997507095337,
              "mrr": 0.549412727355957,
              "top5_acc": 0.6464583277702332,
              "ndcg_5": 0.5611766576766968,
              "top10_acc": 0.7138369679450989,
              "ndcg_10": 0.5830317139625549,
              "best_epoch": 43
            },
            "f1": {
              "accuracy": 0.46354642510414124,
              "accuracy_macro": 0.1010378183906943,
              "f1": 0.09104104340076447,
              "f1_weighted": 0.43813997507095337,
              "mrr": 0.549412727355957,
              "top5_acc": 0.6464583277702332,
              "ndcg_5": 0.5611766576766968,
              "top10_acc": 0.7138369679450989,
              "ndcg_10": 0.5830317139625549,
              "best_epoch": 43
            }
          }
        },
        {
          "accuracy": 0.47461992502212524,
          "accuracy_macro": 0.11178224933377748,
          "f1": 0.1000153049826622,
          "f1_weighted": 0.4490184783935547,
          "mrr": 0.5603687763214111,
          "top5_acc": 0.6579972505569458,
          "ndcg_5": 0.5728774666786194,
          "top10_acc": 0.7224525809288025,
          "ndcg_10": 0.5937475562095642,
          "best_epoch": 40,
          "per_metric_best": {
            "accuracy": {
              "accuracy": 0.4771956503391266,
              "accuracy_macro": 0.11395865885416667,
              "f1": 0.10179372876882553,
              "f1_weighted": 0.45191535353660583,
              "mrr": 0.5616515278816223,
              "top5_acc": 0.6562068462371826,
              "ndcg_5": 0.5732226967811584,
              "top10_acc": 0.7221070528030396,
              "ndcg_10": 0.5945995450019836,
              "best_epoch": 44
            },
            "top5_acc": {
              "accuracy": 0.47461992502212524,
              "accuracy_macro": 0.11178224933377748,
              "f1": 0.1000153049826622,
              "f1_weighted": 0.4490184783935547,
              "mrr": 0.5603687763214111,
              "top5_acc": 0.6579972505569458,
              "ndcg_5": 0.5728774666786194,
              "top10_acc": 0.7224525809288025,
              "ndcg_10": 0.5937475562095642,
              "best_epoch": 40
            },
            "top10_acc": {
              "accuracy": 0.47461992502212524,
              "accuracy_macro": 0.11178224933377748,
              "f1": 0.1000153049826622,
              "f1_weighted": 0.4490184783935547,
              "mrr": 0.5603687763214111,
              "top5_acc": 0.6579972505569458,
              "ndcg_5": 0.5728774666786194,
              "top10_acc": 0.7224525809288025,
              "ndcg_10": 0.5937475562095642,
              "best_epoch": 40
            },
            "mrr": {
              "accuracy": 0.4771956503391266,
              "accuracy_macro": 0.11395865885416667,
              "f1": 0.10179372876882553,
              "f1_weighted": 0.45191535353660583,
              "mrr": 0.5616515278816223,
              "top5_acc": 0.6562068462371826,
              "ndcg_5": 0.5732226967811584,
              "top10_acc": 0.7221070528030396,
              "ndcg_10": 0.5945995450019836,
              "best_epoch": 44
            },
            "f1": {
              "accuracy": 0.47625330090522766,
              "accuracy_macro": 0.11407207096137874,
              "f1": 0.10217198729515076,
              "f1_weighted": 0.45210325717926025,
              "mrr": 0.5612667202949524,
              "top5_acc": 0.6557042598724365,
              "ndcg_5": 0.572761058807373,
              "top10_acc": 0.7216672897338867,
              "ndcg_10": 0.5942046046257019,
              "best_epoch": 47
            }
          }
        },
        {
          "accuracy": 0.4681011438369751,
          "accuracy_macro": 0.11326030814184039,
          "f1": 0.10323450714349747,
          "f1_weighted": 0.4445507824420929,
          "mrr": 0.5563503503799438,
          "top5_acc": 0.6565415263175964,
          "ndcg_5": 0.5696590542793274,
          "top10_acc": 0.7188000679016113,
          "ndcg_10": 0.5898718237876892,
          "best_epoch": 42,
          "per_metric_best": {
            "accuracy": {
              "accuracy": 0.4695146977901459,
              "accuracy_macro": 0.11398343519503,
              "f1": 0.1041993573307991,
              "f1_weighted": 0.4455619752407074,
              "mrr": 0.5571586489677429,
              "top5_acc": 0.6574210524559021,
              "ndcg_5": 0.5705766677856445,
              "top10_acc": 0.7182660698890686,
              "ndcg_10": 0.5903039574623108,
              "best_epoch": 43
            },
            "top5_acc": {
              "accuracy": 0.46907490491867065,
              "accuracy_macro": 0.11344632600483141,
              "f1": 0.10359961539506912,
              "f1_weighted": 0.4453027546405792,
              "mrr": 0.5569443702697754,
              "top5_acc": 0.6581121683120728,
              "ndcg_5": 0.5706585049629211,
              "top10_acc": 0.7185487747192383,
              "ndcg_10": 0.5902237892150879,
              "best_epoch": 49
            },
            "top10_acc": {
              "accuracy": 0.4681011438369751,
              "accuracy_macro": 0.11326030814184039,
              "f1": 0.10323450714349747,
              "f1_weighted": 0.4445507824420929,
              "mrr": 0.5563503503799438,
              "top5_acc": 0.6565415263175964,
              "ndcg_5": 0.5696590542793274,
              "top10_acc": 0.7188000679016113,
              "ndcg_10": 0.5898718237876892,
              "best_epoch": 42
            },
            "mrr": {
              "accuracy": 0.4695146977901459,
              "accuracy_macro": 0.11398343519503,
              "f1": 0.1041993573307991,
              "f1_weighted": 0.4455619752407074,
              "mrr": 0.5571586489677429,
              "top5_acc": 0.6574210524559021,
              "ndcg_5": 0.5705766677856445,
              "top10_acc": 0.7182660698890686,
              "ndcg_10": 0.5903039574623108,
              "best_epoch": 43
            },
            "f1": {
              "accuracy": 0.4695146977901459,
              "accuracy_macro": 0.11398343519503,
              "f1": 0.1041993573307991,
              "f1_weighted": 0.4455619752407074,
              "mrr": 0.5571586489677429,
              "top5_acc": 0.6574210524559021,
              "ndcg_5": 0.5705766677856445,
              "top10_acc": 0.7182660698890686,
              "ndcg_10": 0.5903039574623108,
              "best_epoch": 43
            }
          }
        },
        {
          "accuracy": 0.4678017199039459,
          "accuracy_macro": 0.11253096851835913,
          "f1": 0.10067568719387054,
          "f1_weighted": 0.4427405297756195,
          "mrr": 0.5561092495918274,
          "top5_acc": 0.6571275591850281,
          "ndcg_5": 0.5692428350448608,
          "top10_acc": 0.7246339917182922,
          "ndcg_10": 0.5911657810211182,
          "best_epoch": 41,
          "per_metric_best": {
            "accuracy": {
              "accuracy": 0.46896398067474365,
              "accuracy_macro": 0.11167414936683503,
              "f1": 0.10062708705663681,
              "f1_weighted": 0.4437284469604492,
              "mrr": 0.5570378303527832,
              "top5_acc": 0.6579443216323853,
              "ndcg_5": 0.570240318775177,
              "top10_acc": 0.7237858772277832,
              "ndcg_10": 0.5916420221328735,
              "best_epoch": 43
            },
            "top5_acc": {
              "accuracy": 0.4689011573791504,
              "accuracy_macro": 0.11454811895080887,
              "f1": 0.10092609375715256,
              "f1_weighted": 0.44114989042282104,
              "mrr": 0.5569611191749573,
              "top5_acc": 0.6585411429405212,
              "ndcg_5": 0.5703890919685364,
              "top10_acc": 0.7230633497238159,
              "ndcg_10": 0.5913481116294861,
              "best_epoch": 33
            },
            "top10_acc": {
              "accuracy": 0.4678017199039459,
              "accuracy_macro": 0.11253096851835913,
              "f1": 0.10067568719387054,
              "f1_weighted": 0.4427405297756195,
              "mrr": 0.5561092495918274,
              "top5_acc": 0.6571275591850281,
              "ndcg_5": 0.5692428350448608,
              "top10_acc": 0.7246339917182922,
              "ndcg_10": 0.5911657810211182,
              "best_epoch": 41
            },
            "mrr": {
              "accuracy": 0.46896398067474365,
              "accuracy_macro": 0.11167414936683503,
              "f1": 0.10062708705663681,
              "f1_weighted": 0.4437284469604492,
              "mrr": 0.5570378303527832,
              "top5_acc": 0.6579443216323853,
              "ndcg_5": 0.570240318775177,
              "top10_acc": 0.7237858772277832,
              "ndcg_10": 0.5916420221328735,
              "best_epoch": 43
            },
            "f1": {
              "accuracy": 0.46846139430999756,
              "accuracy_macro": 0.1168443074063679,
              "f1": 0.10351750999689102,
              "f1_weighted": 0.44065457582473755,
              "mrr": 0.5563381314277649,
              "top5_acc": 0.6577558517456055,
              "ndcg_5": 0.5696425437927246,
              "top10_acc": 0.7234717607498169,
              "ndcg_10": 0.5909557938575745,
              "best_epoch": 32
            }
          }
        }
      ],
      "aggregate": {
        "accuracy_mean": 0.46931988596916197,
        "accuracy_std": 0.004977558620710462,
        "top5_acc_mean": 0.6561017513275147,
        "top5_acc_std": 0.006501835758786339,
        "top10_acc_mean": 0.72195383310318,
        "top10_acc_std": 0.005641160217148572,
        "mrr_mean": 0.5566815137863159,
        "mrr_std": 0.004971248379839906,
        "f1_mean": 0.10076362639665604,
        "f1_std": 0.007676700203956236
      },
      "aggregate_per_metric_best": {
        "accuracy_at_accuracy_best_mean": 0.47081509232521057,
        "accuracy_at_accuracy_best_std": 0.005361463805476385,
        "top5_acc_at_accuracy_best_mean": 0.6558756232261658,
        "top5_acc_at_accuracy_best_std": 0.005599223316221601,
        "top10_acc_at_accuracy_best_mean": 0.7211308360099793,
        "top10_acc_at_accuracy_best_std": 0.005291887165739919,
        "mrr_at_accuracy_best_mean": 0.5573462963104248,
        "mrr_at_accuracy_best_std": 0.004965329582479066,
        "f1_at_accuracy_best_mean": 0.1015822097659111,
        "f1_at_accuracy_best_std": 0.006965097438473185,
        "accuracy_at_top5_acc_best_mean": 0.4696654200553894,
        "accuracy_at_top5_acc_best_std": 0.004923616200610546,
        "top5_acc_at_top5_acc_best_mean": 0.6571635007858276,
        "top5_acc_at_top5_acc_best_std": 0.005772971673116402,
        "top10_acc_at_top5_acc_best_mean": 0.7213067412376404,
        "top10_acc_at_top5_acc_best_std": 0.005827704182029036,
        "mrr_at_top5_acc_best_mean": 0.5569622635841369,
        "mrr_at_top5_acc_best_std": 0.004880156931804419,
        "f1_at_top5_acc_best_mean": 0.10091411173343659,
        "f1_at_top5_acc_best_std": 0.0075878311327829025,
        "accuracy_at_top10_acc_best_mean": 0.46931988596916197,
        "accuracy_at_top10_acc_best_std": 0.004977558620710462,
        "top5_acc_at_top10_acc_best_mean": 0.6561017513275147,
        "top5_acc_at_top10_acc_best_std": 0.006501835758786339,
        "top10_acc_at_top10_acc_best_mean": 0.72195383310318,
        "top10_acc_at_top10_acc_best_std": 0.005641160217148572,
        "mrr_at_top10_acc_best_mean": 0.5566815137863159,
        "mrr_at_top10_acc_best_std": 0.004971248379839906,
        "f1_at_top10_acc_best_mean": 0.10076362639665604,
        "f1_at_top10_acc_best_std": 0.007676700203956236,
        "accuracy_at_mrr_best_mean": 0.4706266224384308,
        "accuracy_at_mrr_best_std": 0.005198031741853278,
        "top5_acc_at_mrr_best_mean": 0.6562148690223694,
        "top5_acc_at_mrr_best_std": 0.006047113028534638,
        "top10_acc_at_mrr_best_mean": 0.7214512467384339,
        "top10_acc_at_mrr_best_std": 0.00580912974009278,
        "mrr_at_mrr_best_mean": 0.5574218392372131,
        "mrr_at_mrr_best_std": 0.005045984960506965,
        "f1_at_mrr_best_mean": 0.10168484598398209,
        "f1_at_mrr_best_std": 0.007126660036657491,
        "accuracy_at_f1_best_mean": 0.47024340033531187,
        "accuracy_at_f1_best_std": 0.004870850864529271,
        "top5_acc_at_f1_best_mean": 0.6561206340789795,
        "top5_acc_at_f1_best_std": 0.006101672716998656,
        "top10_acc_at_f1_best_mean": 0.7211622595787048,
        "top10_acc_at_f1_best_std": 0.005533976228943236,
        "mrr_at_f1_best_mean": 0.5570884108543396,
        "mrr_at_f1_best_std": 0.004857803998226659,
        "f1_at_f1_best_mean": 0.1027178019285202,
        "f1_at_f1_best_std": 0.0077186265147385046
      },
      "config": {
        "max_lr": 0.003,
        "label_smoothing": 0.0,
        "input_layernorm": false,
        "overrides": {},
        "input_type": "region"
      }
    }
  }
}