{
  "tag": "T6_4_both",
  "engine": "check2hgi",
  "state": "arizona",
  "meta": {
    "embedding_path": "/home/vitor.oliveira/PoiMtlNet/output/check2hgi/arizona/poi_embeddings.parquet",
    "graph_pickle": "/home/vitor.oliveira/PoiMtlNet/output/check2hgi/arizona/temp/checkin_graph.pt",
    "n_pois": 20666,
    "emb_dim": 64,
    "n_regions_in_data": 1547,
    "n_regions_total": 1547,
    "visit_log_min": 0.0,
    "visit_log_max": 8.835210800170898
  },
  "folds": [
    {
      "fold": 1,
      "n_train": 16532,
      "n_val": 4134,
      "overall": {
        "n": 4134,
        "top1": 0.06700532172230285,
        "top5": 0.1490082244799226,
        "macro_f1": 0.013679282487407674
      },
      "low_visit_q25": {
        "n": 1195,
        "top1": 0.03933054393305439,
        "top5": 0.08702928870292886,
        "macro_f1": 0.011430463327972516
      },
      "mid_visit_q50": {
        "n": 1904,
        "top1": 0.05514705882352941,
        "top5": 0.14233193277310924,
        "macro_f1": 0.013433200238460766
      },
      "high_visit_q75": {
        "n": 1035,
        "top1": 0.12077294685990338,
        "top5": 0.23285024154589373,
        "macro_f1": 0.02467103397927794
      }
    },
    {
      "fold": 2,
      "n_train": 16533,
      "n_val": 4133,
      "overall": {
        "n": 4133,
        "top1": 0.07379627389305589,
        "top5": 0.15485119767723204,
        "macro_f1": 0.01549468189372945
      },
      "low_visit_q25": {
        "n": 1252,
        "top1": 0.04073482428115016,
        "top5": 0.07907348242811502,
        "macro_f1": 0.011704059225704139
      },
      "mid_visit_q50": {
        "n": 1825,
        "top1": 0.059726027397260274,
        "top5": 0.14684931506849316,
        "macro_f1": 0.017294762538841185
      },
      "high_visit_q75": {
        "n": 1056,
        "top1": 0.13731060606060605,
        "top5": 0.2585227272727273,
        "macro_f1": 0.021796846479128572
      }
    },
    {
      "fold": 3,
      "n_train": 16533,
      "n_val": 4133,
      "overall": {
        "n": 4133,
        "top1": 0.07040890394386644,
        "top5": 0.15073796273893056,
        "macro_f1": 0.013981193023749111
      },
      "low_visit_q25": {
        "n": 1242,
        "top1": 0.0322061191626409,
        "top5": 0.0748792270531401,
        "macro_f1": 0.009344943606835346
      },
      "mid_visit_q50": {
        "n": 1813,
        "top1": 0.05791505791505792,
        "top5": 0.1450634307777165,
        "macro_f1": 0.018320329964332225
      },
      "high_visit_q75": {
        "n": 1078,
        "top1": 0.13543599257884972,
        "top5": 0.24768089053803338,
        "macro_f1": 0.024822510510589924
      }
    },
    {
      "fold": 4,
      "n_train": 16533,
      "n_val": 4133,
      "overall": {
        "n": 4133,
        "top1": 0.07113476893297846,
        "top5": 0.15339946769900797,
        "macro_f1": 0.01701268464250215
      },
      "low_visit_q25": {
        "n": 1288,
        "top1": 0.03260869565217391,
        "top5": 0.08074534161490683,
        "macro_f1": 0.0099404629714675
      },
      "mid_visit_q50": {
        "n": 1791,
        "top1": 0.07314349525404802,
        "top5": 0.15633724176437744,
        "macro_f1": 0.023640109672054117
      },
      "high_visit_q75": {
        "n": 1054,
        "top1": 0.11480075901328274,
        "top5": 0.23719165085388993,
        "macro_f1": 0.014350692271829646
      }
    },
    {
      "fold": 5,
      "n_train": 16533,
      "n_val": 4133,
      "overall": {
        "n": 4133,
        "top1": 0.07355431889668522,
        "top5": 0.16041616259375757,
        "macro_f1": 0.01574546028699187
      },
      "low_visit_q25": {
        "n": 1248,
        "top1": 0.03926282051282051,
        "top5": 0.08974358974358974,
        "macro_f1": 0.012893289652000126
      },
      "mid_visit_q50": {
        "n": 1837,
        "top1": 0.06205770277626565,
        "top5": 0.1491562329885683,
        "macro_f1": 0.016382771394619824
      },
      "high_visit_q75": {
        "n": 1048,
        "top1": 0.13454198473282442,
        "top5": 0.2643129770992366,
        "macro_f1": 0.02124104699255087
      }
    }
  ],
  "summary": {
    "overall": {
      "top1": {
        "mean": 0.07117991747777777,
        "std": 0.0027616504563429925,
        "n_folds": 5
      },
      "top5": {
        "mean": 0.15368260303777015,
        "std": 0.004396229200607029,
        "n_folds": 5
      },
      "macro_f1": {
        "mean": 0.015182660466876052,
        "std": 0.0013662685367231448,
        "n_folds": 5
      }
    },
    "low_visit_q25": {
      "top1": {
        "mean": 0.03682860070836798,
        "std": 0.004081012830180213,
        "n_folds": 5
      },
      "top5": {
        "mean": 0.08229418590853611,
        "std": 0.0060346557555733486,
        "n_folds": 5
      },
      "macro_f1": {
        "mean": 0.011062643756795925,
        "std": 0.0014237058118215804,
        "n_folds": 5
      }
    },
    "mid_visit_q50": {
      "top1": {
        "mean": 0.06159786843323225,
        "std": 0.006931680407843615,
        "n_folds": 5
      },
      "top5": {
        "mean": 0.1479476306744529,
        "std": 0.00531289146622756,
        "n_folds": 5
      },
      "macro_f1": {
        "mean": 0.017814234761661624,
        "std": 0.003731934923087799,
        "n_folds": 5
      }
    },
    "high_visit_q75": {
      "top1": {
        "mean": 0.12857245784909327,
        "std": 0.010119173074704337,
        "n_folds": 5
      },
      "top5": {
        "mean": 0.24811169746195622,
        "std": 0.013446338282336191,
        "n_folds": 5
      },
      "macro_f1": {
        "mean": 0.02137642604667539,
        "std": 0.004251057382150021,
        "n_folds": 5
      }
    }
  },
  "n_folds": 5,
  "seed": 42,
  "sampling": {
    "max_pois": null,
    "min_region_size": 1,
    "n_pois_pre_filter": 20666,
    "n_regions_pre_filter": 1547,
    "n_pois_post_filter": 20666,
    "n_regions_post_filter": 1547
  },
  "solver": {
    "max_iter": 1000,
    "tol": 0.001,
    "C": 1.0,
    "name": "lbfgs"
  }
}